{ "backgroundcolor":"#000000",
 "compressionlevel":-1,
 "height":18,
 "infinite":false,
 "layers":[
        {
         "data":[2, 2, 2, 2, 2, 2, 2, 2, 2, 2, 2, 2, 2, 2, 2, 2, 2, 2, 2, 2, 2, 2, 2, 2, 2, 2, 2, 2, 2, 2, 2, 2, 2, 2, 2, 2, 2, 2, 2, 2, 2, 2, 2, 2, 2, 2, 2, 2, 2, 2, 2, 2, 2, 2, 2, 2, 2, 2, 2, 2, 0, 0, 0, 0, 0, 0, 0, 0, 0, 0, 0, 0, 0, 0, 0, 0, 0, 0, 0, 0, 0, 0, 0, 0, 0, 2, 2, 2, 2, 173, 173, 173, 173, 173, 173, 173, 173, 173, 173, 173, 173, 173, 173, 173, 173, 173, 173, 173, 173, 173, 173, 173, 173, 173, 2, 2, 2, 2, 173, 173, 173, 173, 173, 173, 173, 173, 173, 173, 173, 173, 173, 173, 173, 173, 173, 173, 173, 173, 173, 173, 173, 173, 173, 2, 2, 2, 2, 173, 173, 173, 173, 173, 173, 173, 173, 173, 173, 173, 173, 173, 173, 173, 173, 173, 173, 173, 173, 173, 173, 173, 173, 173, 2, 2, 2, 2, 194, 194, 194, 194, 194, 194, 194, 194, 194, 194, 194, 194, 194, 194, 194, 194, 194, 194, 194, 194, 194, 194, 194, 194, 194, 2, 2, 2, 2, 173, 173, 173, 173, 173, 173, 173, 173, 173, 173, 173, 173, 173, 173, 173, 173, 173, 173, 173, 173, 173, 173, 173, 173, 173, 2, 2, 2, 2, 173, 173, 173, 173, 173, 173, 173, 173, 173, 173, 173, 173, 173, 173, 173, 173, 173, 173, 173, 173, 173, 173, 173, 173, 173, 2, 2, 2, 2, 173, 173, 173, 173, 173, 173, 173, 173, 173, 173, 173, 173, 173, 173, 173, 173, 173, 173, 173, 173, 173, 173, 173, 173, 173, 2, 2, 2, 2, 173, 173, 173, 173, 173, 173, 173, 173, 173, 173, 173, 173, 173, 173, 173, 173, 173, 173, 173, 173, 173, 173, 173, 173, 173, 2, 2, 2, 2, 194, 194, 194, 194, 194, 194, 194, 194, 194, 194, 194, 194, 194, 194, 194, 194, 194, 194, 194, 194, 194, 194, 194, 194, 194, 2, 2, 2, 2, 173, 173, 173, 173, 173, 173, 173, 173, 173, 173, 173, 173, 173, 173, 173, 173, 173, 173, 173, 173, 173, 173, 173, 173, 173, 2, 2, 2, 2, 173, 173, 173, 173, 173, 173, 173, 173, 173, 173, 173, 173, 173, 173, 173, 173, 173, 173, 173, 173, 173, 173, 173, 173, 173, 2, 2, 2, 2, 173, 173, 173, 173, 173, 173, 173, 173, 173, 173, 173, 173, 173, 173, 173, 173, 173, 173, 173, 173, 173, 173, 173, 173, 173, 2, 2, 2, 2, 0, 0, 0, 0, 0, 0, 0, 0, 0, 0, 0, 0, 0, 0, 0, 0, 0, 0, 0, 0, 0, 0, 0, 0, 0, 2, 2, 2, 2, 2, 2, 2, 2, 2, 2, 2, 2, 2, 2, 2, 2, 2, 2, 2, 2, 2, 2, 2, 2, 2, 2, 2, 2, 2, 2, 2, 2, 2, 2, 2, 2, 2, 2, 2, 2, 2, 2, 2, 2, 2, 2, 2, 2, 2, 2, 2, 2, 2, 2, 2, 2, 2, 2, 2, 2],
         "height":18,
         "id":1,
         "name":"back",
         "opacity":0.5,
         "type":"tilelayer",
         "visible":true,
         "width":29,
         "x":0,
         "y":0
        }, 
        {
         "data":[0, 0, 0, 0, 0, 0, 0, 0, 0, 0, 0, 0, 0, 0, 0, 0, 0, 0, 0, 0, 0, 0, 0, 0, 0, 0, 0, 0, 0, 0, 0, 0, 0, 0, 0, 0, 0, 0, 0, 0, 0, 0, 0, 0, 0, 0, 0, 0, 0, 0, 0, 0, 0, 0, 0, 0, 0, 0, 0, 0, 174, 174, 174, 174, 174, 174, 174, 174, 174, 174, 174, 174, 174, 174, 174, 174, 174, 174, 174, 174, 174, 174, 174, 174, 174, 0, 0, 0, 0, 0, 0, 0, 0, 0, 0, 0, 0, 0, 0, 0, 0, 0, 0, 0, 0, 0, 0, 0, 0, 0, 0, 0, 0, 0, 0, 0, 0, 0, 0, 0, 0, 0, 0, 0, 0, 0, 0, 0, 0, 0, 0, 0, 0, 0, 0, 0, 0, 0, 0, 0, 0, 0, 0, 0, 0, 0, 0, 0, 0, 0, 0, 0, 0, 0, 0, 0, 0, 0, 0, 0, 0, 0, 0, 0, 0, 0, 0, 0, 0, 0, 0, 0, 0, 0, 0, 0, 0, 0, 0, 0, 0, 0, 0, 0, 0, 0, 0, 0, 0, 0, 0, 0, 0, 0, 0, 0, 0, 0, 0, 0, 0, 0, 0, 0, 0, 0, 237, 237, 237, 0, 0, 0, 0, 0, 0, 0, 0, 0, 0, 0, 0, 0, 0, 0, 0, 0, 0, 0, 0, 0, 0, 0, 0, 0, 0, 0, 0, 0, 0, 0, 0, 0, 0, 0, 0, 0, 0, 0, 0, 0, 0, 0, 0, 0, 0, 0, 0, 0, 0, 0, 0, 0, 0, 0, 0, 0, 0, 0, 0, 0, 0, 0, 0, 0, 0, 0, 0, 0, 0, 0, 0, 0, 0, 0, 0, 0, 0, 0, 0, 0, 0, 0, 0, 0, 0, 0, 0, 0, 0, 0, 0, 0, 0, 0, 0, 0, 0, 0, 0, 0, 0, 0, 0, 0, 0, 0, 0, 0, 0, 0, 0, 0, 0, 0, 0, 0, 0, 0, 0, 0, 0, 0, 0, 0, 0, 0, 0, 0, 0, 0, 0, 0, 0, 0, 0, 0, 0, 0, 0, 0, 0, 0, 0, 0, 0, 0, 0, 0, 0, 0, 0, 0, 0, 0, 0, 0, 0, 0, 0, 0, 0, 0, 0, 0, 0, 0, 0, 0, 0, 0, 0, 0, 0, 0, 0, 0, 0, 0, 0, 0, 0, 0, 0, 0, 0, 0, 0, 0, 0, 0, 0, 0, 0, 0, 0, 0, 0, 0, 0, 0, 0, 0, 0, 0, 0, 0, 0, 0, 0, 0, 0, 0, 0, 0, 0, 0, 0, 0, 0, 0, 0, 0, 0, 0, 0, 0, 0, 174, 174, 174, 174, 174, 174, 174, 174, 174, 174, 174, 174, 174, 174, 174, 174, 174, 174, 174, 174, 174, 174, 174, 174, 174, 0, 0, 0, 0, 0, 0, 0, 0, 0, 0, 0, 0, 0, 0, 0, 0, 0, 0, 0, 0, 0, 0, 0, 0, 0, 0, 0, 0, 0, 0, 0, 0, 0, 0, 0, 0, 0, 0, 0, 0, 0, 0, 0, 0, 0, 0, 0, 0, 0, 0, 0, 0, 0, 0, 0, 0, 0, 0, 0, 0],
         "height":18,
         "id":2,
         "name":"front",
         "opacity":1,
         "type":"tilelayer",
         "visible":true,
         "width":29,
         "x":0,
         "y":0
        }, 
        {
         "draworder":"topdown",
         "id":3,
         "name":"objects",
         "objects":[
                {
                 "gid":4058,
                 "height":8,
                 "id":26,
                 "name":"",
                 "properties":
                    {
                     "parameters":"{ \"detectArea\" : [ [-9999, -9999], [9999, 9999] ], \"detectEntityTypes\" : [ \"player\" ]}"
                    },
                 "propertytypes":
                    {
                     "parameters":"string"
                    },
                 "rotation":0,
                 "type":"",
                 "visible":true,
                 "width":16,
                 "x":40,
                 "y":32
                }, 
                {
                 "gid":4157,
                 "height":16,
                 "id":27,
                 "name":"",
                 "rotation":0,
                 "type":"",
                 "visible":true,
                 "width":16,
                 "x":16,
                 "y":40
                }, 
                {
                 "gid":4325,
                 "height":48,
                 "id":47,
                 "name":"",
                 "rotation":0,
                 "type":"",
                 "visible":true,
                 "width":32,
                 "x":88,
                 "y":72
                }, 
                {
                 "gid":4397,
                 "height":32,
                 "id":72,
                 "name":"",
                 "rotation":0,
                 "type":"",
                 "visible":true,
                 "width":24,
                 "x":56,
                 "y":56
                }, 
                {
                 "gid":4397,
                 "height":32,
                 "id":95,
                 "name":"",
                 "rotation":0,
                 "type":"",
                 "visible":true,
                 "width":24,
                 "x":152,
                 "y":56
                }, 
                {
                 "gid":4896,
                 "height":96,
                 "id":96,
                 "name":"",
                 "rotation":0,
                 "type":"",
                 "visible":true,
                 "width":48,
                 "x":168,
                 "y":120
                }, 
                {
                 "gid":4901,
                 "height":40,
                 "id":97,
                 "name":"",
                 "rotation":0,
                 "type":"",
                 "visible":true,
                 "width":48,
                 "x":96,
                 "y":120
                }, 
                {
                 "gid":2147488543,
                 "height":48,
                 "id":98,
                 "name":"",
                 "rotation":0,
                 "type":"",
                 "visible":true,
                 "width":48,
                 "x":24,
                 "y":120
                }, 
                {
                 "gid":592,
                 "height":16,
                 "id":99,
                 "name":"",
                 "rotation":0,
                 "type":"",
                 "visible":true,
                 "width":24,
                 "x":128,
                 "y":40
                }, 
                {
                 "gid":591,
                 "height":16,
                 "id":101,
                 "name":"",
                 "rotation":0,
                 "type":"",
                 "visible":true,
                 "width":24,
                 "x":24,
                 "y":56
                }],
         "opacity":1,
         "type":"objectgroup",
         "visible":true,
         "x":0,
         "y":0
        }, 
        {
         "draworder":"topdown",
         "id":4,
         "name":"npcs and monsters",
         "objects":[
                {
                 "gid":4271,
                 "height":16,
                 "id":45,
                 "name":"Cultist (Random)",
                 "properties":
                    {
                     "object":"extrainvisiblenpcspawnerworld",
                     "parameters":"{ \"spawner\" : { \"npcSpecies\" : [\"human\"], \"npcTypes\" : [\"cultistbasic\", \"cultistbasic\", \"cultistbasic\", \"cultistbasic\", \"cultistbasic\", \"cultistscientistpet\", \"cultistscientistpet\", \"cultistscientistpet\", \"cultistassault\", \"cultistassault\", \"cultistrocket\" ], \"npcParams\" : { \"aggressive\" : true, \"persistent\" : true }, \"position\" : [0, 2], \"positionVariance\" : [0, 0], \"frequency\" : [0.2, 0.2], \"stock\" : 1, \"trigger\" : \"wire\", \"outOfSight\" : false } }"
                    },
                 "propertytypes":
                    {
                     "object":"string",
                     "parameters":"string"
                    },
                 "rotation":0,
                 "type":"",
                 "visible":true,
                 "width":16,
                 "x":144,
                 "y":104
                }],
         "opacity":1,
         "type":"objectgroup",
         "visible":true,
         "x":0,
         "y":0
        }, 
        {
         "draworder":"topdown",
         "id":5,
         "name":"mods and stagehands",
         "objects":[
                {
                 "gid":13,
                 "height":8,
                 "id":56,
                 "name":"",
                 "rotation":0,
                 "type":"",
                 "visible":true,
                 "width":8,
                 "x":216,
                 "y":120
                }],
         "opacity":1,
         "type":"objectgroup",
         "visible":true,
         "x":0,
         "y":0
        }, 
        {
         "draworder":"topdown",
         "id":6,
         "name":"wires",
         "objects":[
                {
                 "height":0,
                 "id":29,
                 "name":"",
                 "polyline":[
                        {
                         "x":0,
                         "y":0
                        }, 
                        {
                         "x":-32,
                         "y":0
                        }],
                 "rotation":0,
                 "type":"",
                 "visible":true,
                 "width":0,
                 "x":48,
                 "y":24
                }, 
                {
                 "height":0,
                 "id":46,
                 "name":"",
                 "polyline":[
                        {
                         "x":0,
                         "y":0
                        }, 
                        {
                         "x":120,
                         "y":56
                        }],
                 "rotation":0,
                 "type":"",
                 "visible":true,
                 "width":0,
                 "x":24,
                 "y":32
                }, 
                {
                 "height":8,
                 "id":103,
                 "name":"cleaningbot (hostile)",
                 "properties":
                    {
                     "monster":"cleaningbot",
                     "parameters":"{ \"aggressive\" : true }"
                    },
                 "propertytypes":
                    {
                     "monster":"string",
                     "parameters":"string"
                    },
                 "rotation":0,
                 "type":"",
                 "visible":true,
                 "width":8,
                 "x":80,
                 "y":96
                }, 
                {
                 "height":8,
                 "id":104,
                 "name":"cleaningbot (hostile)",
                 "properties":
                    {
                     "monster":"cleaningbot",
                     "parameters":"{ \"aggressive\" : true }"
                    },
                 "propertytypes":
                    {
                     "monster":"string",
                     "parameters":"string"
                    },
                 "rotation":0,
                 "type":"",
                 "visible":true,
                 "width":8,
                 "x":32,
                 "y":32
                }],
         "opacity":1,
         "type":"objectgroup",
         "visible":true,
         "x":0,
         "y":0
        }],
 "nextlayerid":7,
 "nextobjectid":105,
 "orientation":"orthogonal",
 "renderorder":"right-down",
 "tiledversion":"1.4.2",
 "tileheight":8,
 "tilesets":[
        {
         "firstgid":1,
         "source":"..\/..\/..\/..\/..\/assets\/packed\/tilesets\/packed\/miscellaneous.json"
        }, 
        {
         "firstgid":25,
         "source":"..\/..\/..\/..\/..\/assets\/packed\/tilesets\/packed\/materials.json"
        }, 
        {
         "firstgid":222,
         "source":"..\/..\/..\/..\/..\/assets\/packed\/tilesets\/packed\/supports.json"
        }, 
        {
         "firstgid":259,
         "source":"..\/..\/..\/..\/..\/assets\/packed\/tilesets\/packed\/liquids.json"
        }, 
        {
         "firstgid":287,
         "source":"..\/..\/..\/..\/..\/assets\/packed\/tilesets\/packed\/objects-by-category\/breakable.json"
        }, 
        {
         "firstgid":597,
         "source":"..\/..\/..\/..\/..\/assets\/packed\/tilesets\/packed\/objects-by-category\/bug.json"
        }, 
        {
         "firstgid":640,
         "source":"..\/..\/..\/..\/..\/assets\/packed\/tilesets\/packed\/objects-by-category\/crafting.json"
        }, 
        {
         "firstgid":720,
         "source":"..\/..\/..\/..\/..\/assets\/packed\/tilesets\/packed\/objects-by-category\/decorative.json"
        }, 
        {
         "firstgid":2161,
         "source":"..\/..\/..\/..\/..\/assets\/packed\/tilesets\/packed\/objects-by-category\/door.json"
        }, 
        {
         "firstgid":2293,
         "source":"..\/..\/..\/..\/..\/assets\/packed\/tilesets\/packed\/objects-by-category\/furniture.json"
        }, 
        {
         "firstgid":2647,
         "source":"..\/..\/..\/..\/..\/assets\/packed\/tilesets\/packed\/objects-by-category\/light.json"
        }, 
        {
         "firstgid":3105,
         "source":"..\/..\/..\/..\/..\/assets\/packed\/tilesets\/packed\/objects-by-category\/other.json"
        }, 
        {
         "firstgid":3417,
         "source":"..\/..\/..\/..\/..\/assets\/packed\/tilesets\/packed\/objects-by-category\/railpoint.json"
        }, 
        {
         "firstgid":3422,
         "source":"..\/..\/..\/..\/..\/assets\/packed\/tilesets\/packed\/objects-by-category\/refinery.json"
        }, 
        {
         "firstgid":3423,
         "source":"..\/..\/..\/..\/..\/assets\/packed\/tilesets\/packed\/objects-by-category\/seed.json"
        }, 
        {
         "firstgid":3499,
         "source":"..\/..\/..\/..\/..\/assets\/packed\/tilesets\/packed\/objects-by-category\/spawner.json"
        }, 
        {
         "firstgid":3515,
         "source":"..\/..\/..\/..\/..\/assets\/packed\/tilesets\/packed\/objects-by-category\/storage.json"
        }, 
        {
         "firstgid":3749,
         "source":"..\/..\/..\/..\/..\/assets\/packed\/tilesets\/packed\/objects-by-category\/techmanagement.json"
        }, 
        {
         "firstgid":3750,
         "source":"..\/..\/..\/..\/..\/assets\/packed\/tilesets\/packed\/objects-by-category\/trap.json"
        }, 
        {
         "firstgid":3954,
         "source":"..\/..\/..\/..\/..\/assets\/packed\/tilesets\/packed\/objects-by-category\/wire.json"
        }, 
        {
         "firstgid":4176,
         "source":"..\/..\/..\/tilesets\/extradungeons-custom\/modstuff.json"
        }, 
        {
         "firstgid":4237,
         "source":"..\/..\/..\/tilesets\/extradungeons-custom\/modstuff.json"
        }, 
        {
         "firstgid":4298,
         "source":"..\/..\/..\/..\/..\/assets\/packed\/tilesets\/packed\/objects-by-colonytag\/wreck.json"
        }, 
        {
         "firstgid":4325,
         "source":"..\/..\/..\/..\/..\/assets\/packed\/tilesets\/packed\/objects-by-colonytag\/cultist.json"
        }, 
        {
         "firstgid":4334,
         "source":"..\/..\/..\/..\/..\/assets\/packed\/tilesets\/packed\/objects-by-colonytag\/humanbunker.json"
        }, 
        {
         "firstgid":4406,
         "source":"..\/..\/..\/..\/..\/assets\/packed\/tilesets\/packed\/objects-by-colonytag\/humanprison.json"
        }, 
        {
         "firstgid":4500,
         "source":"..\/..\/..\/..\/..\/assets\/packed\/tilesets\/packed\/objects-by-race\/novakid.json"
        }, 
        {
         "firstgid":4564,
         "source":"..\/..\/..\/..\/..\/assets\/packed\/tilesets\/packed\/objects-by-race\/human.json"
        }, 
        {
         "firstgid":4852,
         "source":"..\/..\/..\/..\/..\/assets\/packed\/tilesets\/packed\/objects-by-colonytag\/foundry.json"
        }, 
        {
         "firstgid":4891,
         "source":"..\/..\/..\/tilesets\/frackinuniverse-custom\/fu_mine.json"
        }],
 "tilewidth":8,
 "type":"map",
 "version":1.1,
 "width":29
}