{ "backgroundcolor":"#000000",
 "compressionlevel":-1,
 "height":35,
 "infinite":false,
 "layers":[
        {
         "compression":"zlib",
         "data":"eJztmtsNwjAMRdNxsg2TdZLuwCCMwQIQCUuV5TwcOyHQe6T706iNdTBt+ggB\/BLHO\/fOAB1HsPmGcx3cdxTy2OTtMcC5Fu57F5J882203x7gXAP3ndz2BM7baOlvKef+psB5nVJ\/a33DeZ1cf\/f6hvM60vqktCap5Sq+LWvos+9cT6exI5PoNP830oPX3Ff03ePca15yJ2W1Ma+ae5xLc7fWwWsvXSNz18vW\/TzHtDWXxrTOpbk17q7uW+t8Fd9e5zVv397n85V8PzdbRvnW1gHfc32XnFt93z75Jd+ami11wfdc35LzlXzPul5qfVuzou\/afp5j2po1YzzcufV+Z9V7SG39Xsc\/p9Tf1qTj535jqlFKdJp\/1UjA9zzXFs5rWfoP4fn3GKg\/yRH1Mt7vjIH7xvvLseT6uxbJN1zXKfU3vj\/xp6W\/8X2VH9y3tN4orVXIN2iD+15hffrvWHwDMJoXa3fyxg==",
         "encoding":"base64",
         "height":35,
         "id":1,
         "name":"back",
         "opacity":0.5,
         "type":"tilelayer",
         "visible":true,
         "width":92,
         "x":0,
         "y":0
        }, 
        {
         "compression":"zlib",
         "data":"eJztmsENgzAMRanUZdh\/gE7UUxegl6qoAhJ\/O04o70m+2uHFMlFgmuBMzO94iAE25snnG+caijuc66jecK7hcYZzO15fOLcR4QrnZX7PJ15wXgbfGp4zdG0879uRUbtVjOr6aG29nWU777nXvYhYs\/rs3tpX9b3OY8mV7fszt3sS2SNW5\/R3XL6anPiO4XX7RsvaV58na2qcn7E\/R6bkHN\/xHDnP9j3CPMlg7x1Kf7djyzm+21Dq79bxj\/dVNVHai8y6WbVHcu2B++881O87e+cTfNcR4QjX9Xg94dqGZ57g2o7qC9caijNc2+H\/2Hz4\/xtGZgFKGKPd",
         "encoding":"base64",
         "height":35,
         "id":2,
         "name":"front",
         "opacity":1,
         "type":"tilelayer",
         "visible":true,
         "width":92,
         "x":0,
         "y":0
        }, 
        {
         "draworder":"topdown",
         "id":3,
         "name":"objects",
         "objects":[
                {
                 "gid":205,
                 "height":80,
                 "id":22,
                 "name":"",
                 "rotation":0,
                 "type":"",
                 "visible":true,
                 "width":64,
                 "x":48,
                 "y":184
                }, 
                {
                 "gid":201,
                 "height":40,
                 "id":24,
                 "name":"",
                 "rotation":0,
                 "type":"",
                 "visible":true,
                 "width":48,
                 "x":120,
                 "y":184
                }, 
                {
                 "gid":201,
                 "height":40,
                 "id":25,
                 "name":"",
                 "rotation":0,
                 "type":"",
                 "visible":true,
                 "width":48,
                 "x":480,
                 "y":184
                }, 
                {
                 "gid":203,
                 "height":24,
                 "id":26,
                 "name":"",
                 "rotation":0,
                 "type":"",
                 "visible":true,
                 "width":32,
                 "x":168,
                 "y":168
                }, 
                {
                 "gid":222,
                 "height":41,
                 "id":27,
                 "name":"",
                 "rotation":0,
                 "type":"",
                 "visible":true,
                 "width":60,
                 "x":152,
                 "y":256
                }, 
                {
                 "gid":219,
                 "height":40,
                 "id":28,
                 "name":"",
                 "rotation":0,
                 "type":"",
                 "visible":true,
                 "width":32,
                 "x":104,
                 "y":64
                }, 
                {
                 "gid":219,
                 "height":40,
                 "id":29,
                 "name":"",
                 "rotation":0,
                 "type":"",
                 "visible":true,
                 "width":32,
                 "x":104,
                 "y":256
                }, 
                {
                 "gid":204,
                 "height":24,
                 "id":30,
                 "name":"",
                 "rotation":0,
                 "type":"",
                 "visible":true,
                 "width":24,
                 "x":448,
                 "y":168
                }, 
                {
                 "gid":200,
                 "height":24,
                 "id":31,
                 "name":"",
                 "rotation":0,
                 "type":"",
                 "visible":true,
                 "width":16,
                 "x":536,
                 "y":168
                }, 
                {
                 "gid":199,
                 "height":24,
                 "id":32,
                 "name":"",
                 "rotation":0,
                 "type":"",
                 "visible":true,
                 "width":32,
                 "x":584,
                 "y":184
                }, 
                {
                 "gid":1005,
                 "height":8,
                 "id":33,
                 "name":"",
                 "rotation":0,
                 "type":"",
                 "visible":true,
                 "width":16,
                 "x":32,
                 "y":112
                }, 
                {
                 "gid":1005,
                 "height":8,
                 "id":34,
                 "name":"",
                 "rotation":0,
                 "type":"",
                 "visible":true,
                 "width":16,
                 "x":112,
                 "y":112
                }, 
                {
                 "gid":1005,
                 "height":8,
                 "id":35,
                 "name":"",
                 "rotation":0,
                 "type":"",
                 "visible":true,
                 "width":16,
                 "x":176,
                 "y":104
                }, 
                {
                 "gid":1005,
                 "height":8,
                 "id":36,
                 "name":"",
                 "rotation":0,
                 "type":"",
                 "visible":true,
                 "width":16,
                 "x":176,
                 "y":32
                }, 
                {
                 "gid":1005,
                 "height":8,
                 "id":37,
                 "name":"",
                 "rotation":0,
                 "type":"",
                 "visible":true,
                 "width":16,
                 "x":176,
                 "y":208
                }, 
                {
                 "gid":1005,
                 "height":8,
                 "id":38,
                 "name":"",
                 "rotation":0,
                 "type":"",
                 "visible":true,
                 "width":16,
                 "x":232,
                 "y":104
                }, 
                {
                 "gid":1005,
                 "height":8,
                 "id":39,
                 "name":"",
                 "rotation":0,
                 "type":"",
                 "visible":true,
                 "width":16,
                 "x":288,
                 "y":104
                }, 
                {
                 "gid":1005,
                 "height":8,
                 "id":40,
                 "name":"",
                 "rotation":0,
                 "type":"",
                 "visible":true,
                 "width":16,
                 "x":344,
                 "y":104
                }, 
                {
                 "gid":1005,
                 "height":8,
                 "id":41,
                 "name":"",
                 "rotation":0,
                 "type":"",
                 "visible":true,
                 "width":16,
                 "x":400,
                 "y":104
                }, 
                {
                 "gid":1005,
                 "height":8,
                 "id":42,
                 "name":"",
                 "rotation":0,
                 "type":"",
                 "visible":true,
                 "width":16,
                 "x":456,
                 "y":104
                }, 
                {
                 "gid":1005,
                 "height":8,
                 "id":43,
                 "name":"",
                 "rotation":0,
                 "type":"",
                 "visible":true,
                 "width":16,
                 "x":536,
                 "y":104
                }, 
                {
                 "gid":1005,
                 "height":8,
                 "id":44,
                 "name":"",
                 "rotation":0,
                 "type":"",
                 "visible":true,
                 "width":16,
                 "x":592.204545454546,
                 "y":104
                }, 
                {
                 "gid":234,
                 "height":16,
                 "id":45,
                 "name":"",
                 "rotation":0,
                 "type":"",
                 "visible":true,
                 "width":32,
                 "x":528,
                 "y":136
                }],
         "opacity":1,
         "type":"objectgroup",
         "visible":true,
         "x":0,
         "y":0
        }, 
        {
         "draworder":"topdown",
         "id":4,
         "name":"wiring",
         "objects":[],
         "opacity":1,
         "type":"objectgroup",
         "visible":true,
         "x":0,
         "y":0
        }],
 "nextlayerid":5,
 "nextobjectid":46,
 "orientation":"orthogonal",
 "renderorder":"right-down",
 "tiledversion":"1.5.0",
 "tileheight":8,
 "tilesets":[
        {
         "firstgid":1,
         "source":"..\/..\/..\/..\/assets\/packed\/tilesets\/packed\/materials.json"
        }, 
        {
         "firstgid":198,
         "source":"..\/..\/tilesets\/frackinuniverse-custom\/fu_byos.json"
        }, 
        {
         "firstgid":206,
         "source":"..\/..\/tilesets\/frackinuniverse-custom\/BYOS_Objects.json"
        }, 
        {
         "firstgid":235,
         "source":"..\/..\/tilesets\/fu_mastermaterials.json"
        }, 
        {
         "firstgid":795,
         "source":"..\/..\/..\/..\/assets\/packed\/tilesets\/packed\/objects-by-category\/light.json"
        }, 
        {
         "firstgid":1253,
         "source":"..\/..\/..\/..\/assets\/packed\/tilesets\/packed\/supports.json"
        }],
 "tilewidth":8,
 "type":"map",
 "version":1.1,
 "width":92
}