{ "backgroundcolor":"#000000",
 "compressionlevel":-1,
 "height":63,
 "infinite":false,
 "layers":[
        {
         "compression":"zlib",
         "data":"eJzt2lFqwkAUheHsoS\/uwc30qU9dRt8Vuh6zjLotDRiQkDPTyYy5947\/gQ+KxgjlJxD1OgzDFQCwxXnyd\/8bsEKf8Iw+4Rl9wjP6hGf0iRTr0SfoE1FZjz5Bn4jKevQJ+kRU1qNP0Ceish59xqTW6vw\/C1ajz5jU6BMeqLU6\/3h3fBgT7\/fq0WdMavQJD9ToEx6o0Sc8UBsr5fqsPX8p+oxJ7Vgp12fp+abXfjwZC19PnzGp7d3nYchfA5d9KoeV89NnTGp79zk995Ww1mfqWPrsgxp9wgM1+oQHaq36VN9v0ics+\/x+WF4\/58fpE5H65P4dnvvM4fPP96RGn\/BArfb7xFyffL+Jmj5bnZ\/fJ8Nzn+rzz71HnzGp0Sc8UKNPeFdzP5Lrk\/sj1PoVHvfh58kojpnPoe6P5uMuifdJPVeKPvvTok91\/aRP0Cd99syiz8tCrrvl8ep19Nkfqz5Lrotrx9Pne2jRp7o\/Utc6+sQefea+fy\/pjT5Bn\/b\/b9AnffaD39fBs88KuT5rzr0FfSLFevQJ+kRU1qNP0Ceish59ItfnaVjfSWg5+kTO3J16XGnx3vSJ\/8r12Hmfe74XKr2yyWf0Cc\/oE54l+gQAbHADYTzBtw==",
         "encoding":"base64",
         "height":63,
         "id":1,
         "name":"back",
         "opacity":0.5,
         "type":"tilelayer",
         "visible":true,
         "width":168,
         "x":0,
         "y":0
        }, 
        {
         "compression":"zlib",
         "data":"eJzt28FNxDAUhOEtg17SBAVQAWcunOiCMiiCA01QDAhpI0XWxmM\/O54s\/kf6LitiWU9DSMBcLoQQQlryDRipuPeHuam494e5qbj3h7mpuPeHuam494e5qbj3h7mpuPeHuam494e5qbj3h7mpuPeHuam494fxPnc49qLinhXG2uumq6Mq7nlhrIerl8T6+ej9qLjnhbHWHn4k6CfO4OnqK7F+Pno\/Ku55oZ56hsxR\/WxZO0LFPWuM6yb9xNH23m9KrdenaV03SsU9b8T6mb7flFL9jK4bpeKeN+rs\/XwupX6+R9eNUnHPG\/QzF\/e8QT9zcc8b9DMX97xBP3Nxzxv0Mxf3vEE\/c3HPG2P7qXpCP3FP\/fxJlPZKXU8\/\/yfunzizo\/u5hn7C2c+a0E+UWs9xPAet16fPha3rRqm4541YP9+D1Pml6LpRKu55o07reUv1+0\/Of6JF63lL1U\/Of6JVy\/tIj78fvVZ+nvs6Ffes4eln+n5EP3Gmfh5x\/4xQcc8a9DMX96xxf\/3sScU9a9DPXNyzhqefLe9H9BNH9bOkI\/QTZ+rntifcP3G2fm5DP3G2fva+f\/49z+79PTM9Q6\/injX8\/dymRzcfhZr\/E3HPGnVaz2PsnfPk\/Cd6aD3PtnfOk\/Of6GH0+TfO16HG2wGWjdY1aq9Tcc8bx\/S0pC\/LpU83W6i454w+PT2qa6XfD\/QTJXr289b6uXtw5J6u4p4njhftYum6yw2554jt16i4Z4fxWjqp1lTPuEtynYp7Vpibint\/mBshhJC++QWvc89p",
         "encoding":"base64",
         "height":63,
         "id":2,
         "name":"front",
         "opacity":1,
         "type":"tilelayer",
         "visible":true,
         "width":168,
         "x":0,
         "y":0
        }, 
        {
         "color":"#5555ff",
         "draworder":"topdown",
         "id":3,
         "name":"mods",
         "objects":[
                {
                 "height":8,
                 "id":999,
                 "name":"",
                 "properties":[
                        {
                         "name":"back",
                         "type":"string",
                         "value":"outpostsupport"
                        }, 
                        {
                         "name":"colorVariant",
                         "type":"string",
                         "value":"6"
                        }],
                 "rotation":0,
                 "type":"",
                 "visible":true,
                 "width":224,
                 "x":1072,
                 "y":264
                }, 
                {
                 "height":8,
                 "id":1001,
                 "name":"",
                 "properties":[
                        {
                         "name":"back",
                         "type":"string",
                         "value":"outpostsupport"
                        }, 
                        {
                         "name":"colorVariant",
                         "type":"string",
                         "value":"6"
                        }],
                 "rotation":0,
                 "type":"",
                 "visible":true,
                 "width":112,
                 "x":896,
                 "y":264
                }, 
                {
                 "gid":5764,
                 "height":40,
                 "id":1002,
                 "name":"",
                 "rotation":0,
                 "type":"",
                 "visible":true,
                 "width":48,
                 "x":1040,
                 "y":400
                }, 
                {
                 "gid":5764,
                 "height":40,
                 "id":1003,
                 "name":"",
                 "rotation":0,
                 "type":"",
                 "visible":true,
                 "width":48,
                 "x":992,
                 "y":400
                }, 
                {
                 "gid":5764,
                 "height":40,
                 "id":1004,
                 "name":"",
                 "rotation":0,
                 "type":"",
                 "visible":true,
                 "width":48,
                 "x":992,
                 "y":272
                }, 
                {
                 "height":8,
                 "id":1043,
                 "name":"",
                 "properties":[
                        {
                         "name":"back",
                         "type":"string",
                         "value":"slopedrustypanel"
                        }, 
                        {
                         "name":"colorVariant",
                         "type":"string",
                         "value":"7"
                        }, 
                        {
                         "name":"front",
                         "type":"string",
                         "value":"slopedrustypanel"
                        }],
                 "rotation":0,
                 "type":"",
                 "visible":true,
                 "width":128,
                 "x":880,
                 "y":152
                }, 
                {
                 "height":8,
                 "id":1044,
                 "name":"",
                 "properties":[
                        {
                         "name":"back",
                         "type":"string",
                         "value":"slopedrustypanel"
                        }, 
                        {
                         "name":"colorVariant",
                         "type":"string",
                         "value":"7"
                        }, 
                        {
                         "name":"front",
                         "type":"string",
                         "value":"slopedrustypanel"
                        }],
                 "rotation":0,
                 "type":"",
                 "visible":true,
                 "width":120,
                 "x":888,
                 "y":144
                }, 
                {
                 "height":16,
                 "id":1045,
                 "name":"",
                 "properties":[
                        {
                         "name":"back",
                         "type":"string",
                         "value":"slopedrustypanel"
                        }, 
                        {
                         "name":"colorVariant",
                         "type":"string",
                         "value":"7"
                        }, 
                        {
                         "name":"front",
                         "type":"string",
                         "value":"slopedrustypanel"
                        }],
                 "rotation":0,
                 "type":"",
                 "visible":true,
                 "width":224,
                 "x":1072,
                 "y":144
                }, 
                {
                 "height":8,
                 "id":1046,
                 "name":"",
                 "properties":[
                        {
                         "name":"back",
                         "type":"string",
                         "value":"slopedrustypanel"
                        }, 
                        {
                         "name":"colorVariant",
                         "type":"string",
                         "value":"7"
                        }, 
                        {
                         "name":"front",
                         "type":"string",
                         "value":"slopedrustypanel"
                        }],
                 "rotation":0,
                 "type":"",
                 "visible":true,
                 "width":64,
                 "x":1008,
                 "y":112
                }, 
                {
                 "height":8,
                 "id":1047,
                 "name":"",
                 "properties":[
                        {
                         "name":"back",
                         "type":"string",
                         "value":"slopedrustypanel"
                        }, 
                        {
                         "name":"colorVariant",
                         "type":"string",
                         "value":"7"
                        }, 
                        {
                         "name":"front",
                         "type":"string",
                         "value":"slopedrustypanel"
                        }],
                 "rotation":0,
                 "type":"",
                 "visible":true,
                 "width":48,
                 "x":1016,
                 "y":104
                }, 
                {
                 "height":8,
                 "id":1069,
                 "name":"",
                 "properties":[
                        {
                         "name":"back",
                         "type":"string",
                         "value":"ironblock"
                        }, 
                        {
                         "name":"colorVariant",
                         "type":"string",
                         "value":"7"
                        }],
                 "rotation":0,
                 "type":"",
                 "visible":true,
                 "width":8,
                 "x":1256,
                 "y":192
                }, 
                {
                 "height":8,
                 "id":1070,
                 "name":"",
                 "properties":[
                        {
                         "name":"back",
                         "type":"string",
                         "value":"ironblock"
                        }, 
                        {
                         "name":"colorVariant",
                         "type":"string",
                         "value":"7"
                        }],
                 "rotation":0,
                 "type":"",
                 "visible":true,
                 "width":8,
                 "x":1256,
                 "y":240
                }, 
                {
                 "height":8,
                 "id":1071,
                 "name":"",
                 "properties":[
                        {
                         "name":"back",
                         "type":"string",
                         "value":"ironblock"
                        }, 
                        {
                         "name":"colorVariant",
                         "type":"string",
                         "value":"7"
                        }],
                 "rotation":0,
                 "type":"",
                 "visible":true,
                 "width":8,
                 "x":1104,
                 "y":240
                }, 
                {
                 "height":8,
                 "id":1072,
                 "name":"",
                 "properties":[
                        {
                         "name":"back",
                         "type":"string",
                         "value":"ironblock"
                        }, 
                        {
                         "name":"colorVariant",
                         "type":"string",
                         "value":"7"
                        }],
                 "rotation":0,
                 "type":"",
                 "visible":true,
                 "width":8,
                 "x":1104,
                 "y":192
                }, 
                {
                 "height":288,
                 "id":1074,
                 "name":"",
                 "properties":[
                        {
                         "name":"parameters",
                         "type":"string",
                         "value":"{ \"radioMessage\" : \"peacekeeper05\" }"
                        }, 
                        {
                         "name":"stagehand",
                         "type":"string",
                         "value":"radiomessage"
                        }],
                 "rotation":0,
                 "type":"",
                 "visible":true,
                 "width":328,
                 "x":552,
                 "y":152
                }],
         "opacity":1,
         "type":"objectgroup",
         "visible":true,
         "x":0,
         "y":0
        }, 
        {
         "color":"#ff0000",
         "draworder":"topdown",
         "id":4,
         "name":"objects",
         "objects":[
                {
                 "gid":8715,
                 "height":96,
                 "id":859,
                 "name":"",
                 "rotation":0,
                 "type":"",
                 "visible":true,
                 "width":16,
                 "x":880,
                 "y":400
                }, 
                {
                 "gid":6280,
                 "height":8,
                 "id":867,
                 "name":"",
                 "rotation":0,
                 "type":"",
                 "visible":true,
                 "width":16,
                 "x":944,
                 "y":312
                }, 
                {
                 "gid":8851,
                 "height":64,
                 "id":994,
                 "name":"",
                 "rotation":0,
                 "type":"",
                 "visible":true,
                 "width":56,
                 "x":896,
                 "y":272
                }, 
                {
                 "gid":2146,
                 "height":32,
                 "id":995,
                 "name":"",
                 "rotation":0,
                 "type":"",
                 "visible":true,
                 "width":32,
                 "x":936,
                 "y":360
                }, 
                {
                 "gid":5764,
                 "height":40,
                 "id":997,
                 "name":"",
                 "rotation":0,
                 "type":"",
                 "visible":true,
                 "width":48,
                 "x":1040,
                 "y":272
                }, 
                {
                 "gid":8847,
                 "height":20,
                 "id":1005,
                 "name":"",
                 "rotation":0,
                 "type":"",
                 "visible":true,
                 "width":16,
                 "x":1136,
                 "y":272
                }, 
                {
                 "height":8,
                 "id":1007,
                 "name":"",
                 "properties":[
                        {
                         "name":"npc",
                         "type":"string",
                         "value":"apex, avian, floran, glitch, human, hylotl, novakid"
                        }, 
                        {
                         "name":"typeName",
                         "type":"string",
                         "value":"peacekeepervillager"
                        }],
                 "rotation":0,
                 "type":"",
                 "visible":true,
                 "width":8,
                 "x":1080,
                 "y":384
                }, 
                {
                 "gid":8843,
                 "height":16,
                 "id":1009,
                 "name":"",
                 "rotation":0,
                 "type":"",
                 "visible":true,
                 "width":8,
                 "x":1192,
                 "y":256
                }, 
                {
                 "gid":2147492495,
                 "height":20,
                 "id":1010,
                 "name":"",
                 "rotation":0,
                 "type":"",
                 "visible":true,
                 "width":16,
                 "x":1224,
                 "y":272
                }, 
                {
                 "gid":8842,
                 "height":16,
                 "id":1011,
                 "name":"",
                 "rotation":0,
                 "type":"",
                 "visible":true,
                 "width":56,
                 "x":1160,
                 "y":272
                }, 
                {
                 "gid":6370,
                 "height":8,
                 "id":1019,
                 "name":"",
                 "rotation":0,
                 "type":"",
                 "visible":true,
                 "width":24,
                 "x":936,
                 "y":184
                }, 
                {
                 "gid":210,
                 "height":8,
                 "id":1028,
                 "name":"",
                 "rotation":0,
                 "type":"",
                 "visible":true,
                 "width":8,
                 "x":1296,
                 "y":400
                }, 
                {
                 "gid":8755,
                 "height":56,
                 "id":1029,
                 "name":"",
                 "rotation":0,
                 "type":"",
                 "visible":true,
                 "width":60,
                 "x":1016,
                 "y":104
                }, 
                {
                 "height":8,
                 "id":1037,
                 "name":"",
                 "properties":[
                        {
                         "name":"npc",
                         "type":"string",
                         "value":"apex, avian, floran, glitch, human, hylotl, novakid"
                        }, 
                        {
                         "name":"typeName",
                         "type":"string",
                         "value":"peacekeepervillager"
                        }],
                 "rotation":0,
                 "type":"",
                 "visible":true,
                 "width":8,
                 "x":1272,
                 "y":240
                }, 
                {
                 "height":8,
                 "id":1038,
                 "name":"",
                 "properties":[
                        {
                         "name":"npc",
                         "type":"string",
                         "value":"apex, avian, floran, glitch, human, hylotl, novakid"
                        }, 
                        {
                         "name":"typeName",
                         "type":"string",
                         "value":"peacekeepervillager"
                        }],
                 "rotation":0,
                 "type":"",
                 "visible":true,
                 "width":8,
                 "x":1096,
                 "y":232
                }, 
                {
                 "gid":6602,
                 "height":8,
                 "id":1039,
                 "name":"",
                 "rotation":0,
                 "type":"",
                 "visible":true,
                 "width":16,
                 "x":1032,
                 "y":288
                }, 
                {
                 "gid":6602,
                 "height":8,
                 "id":1040,
                 "name":"",
                 "rotation":0,
                 "type":"",
                 "visible":true,
                 "width":16,
                 "x":1032,
                 "y":232
                }, 
                {
                 "gid":6602,
                 "height":8,
                 "id":1041,
                 "name":"",
                 "rotation":0,
                 "type":"",
                 "visible":true,
                 "width":16,
                 "x":1032,
                 "y":368
                }, 
                {
                 "gid":3745,
                 "height":16,
                 "id":1048,
                 "name":"",
                 "rotation":0,
                 "type":"",
                 "visible":true,
                 "width":16,
                 "x":984,
                 "y":320
                }, 
                {
                 "gid":6651,
                 "height":40,
                 "id":1050,
                 "name":"",
                 "rotation":0,
                 "type":"",
                 "visible":true,
                 "width":40,
                 "x":1168,
                 "y":232
                }, 
                {
                 "gid":7052,
                 "height":16,
                 "id":1055,
                 "name":"",
                 "rotation":0,
                 "type":"",
                 "visible":true,
                 "width":8,
                 "x":1120,
                 "y":240
                }, 
                {
                 "gid":7062,
                 "height":16,
                 "id":1056,
                 "name":"",
                 "rotation":0,
                 "type":"",
                 "visible":true,
                 "width":8,
                 "x":1248,
                 "y":240
                }, 
                {
                 "gid":7174,
                 "height":16,
                 "id":1058,
                 "name":"",
                 "rotation":0,
                 "type":"",
                 "visible":true,
                 "width":8,
                 "x":1240,
                 "y":240
                }, 
                {
                 "gid":6652,
                 "height":8,
                 "id":1061,
                 "name":"",
                 "rotation":0,
                 "type":"",
                 "visible":true,
                 "width":16,
                 "x":1208,
                 "y":184
                }, 
                {
                 "gid":6652,
                 "height":8,
                 "id":1062,
                 "name":"",
                 "rotation":0,
                 "type":"",
                 "visible":true,
                 "width":16,
                 "x":1152,
                 "y":184
                }, 
                {
                 "gid":6652,
                 "height":8,
                 "id":1063,
                 "name":"",
                 "rotation":0,
                 "type":"",
                 "visible":true,
                 "width":16,
                 "x":1096,
                 "y":184
                }, 
                {
                 "gid":6652,
                 "height":8,
                 "id":1064,
                 "name":"",
                 "rotation":0,
                 "type":"",
                 "visible":true,
                 "width":16,
                 "x":1256,
                 "y":184
                }, 
                {
                 "gid":2147490602,
                 "height":40,
                 "id":1075,
                 "name":"",
                 "rotation":0,
                 "type":"",
                 "visible":true,
                 "width":48,
                 "x":1216,
                 "y":384
                }, 
                {
                 "gid":4194,
                 "height":48,
                 "id":1076,
                 "name":"",
                 "rotation":0,
                 "type":"",
                 "visible":true,
                 "width":64,
                 "x":1096,
                 "y":400
                }, 
                {
                 "gid":6280,
                 "height":8,
                 "id":1078,
                 "name":"",
                 "rotation":0,
                 "type":"",
                 "visible":true,
                 "width":16,
                 "x":1096,
                 "y":312
                }, 
                {
                 "gid":6280,
                 "height":8,
                 "id":1079,
                 "name":"",
                 "rotation":0,
                 "type":"",
                 "visible":true,
                 "width":16,
                 "x":1256,
                 "y":312
                }, 
                {
                 "gid":5619,
                 "height":24,
                 "id":1080,
                 "name":"",
                 "rotation":0,
                 "type":"",
                 "visible":true,
                 "width":24,
                 "x":944,
                 "y":208
                }, 
                {
                 "gid":7522,
                 "height":64,
                 "id":1082,
                 "name":"",
                 "properties":[
                        {
                         "name":"parameters",
                         "type":"string",
                         "value":"{ \"interactData\" : \"\/interface\/warping\/peacekeeper.config\" }"
                        }],
                 "rotation":0,
                 "type":"",
                 "visible":true,
                 "width":32,
                 "x":960,
                 "y":272
                }],
         "opacity":1,
         "type":"objectgroup",
         "visible":true,
         "x":0,
         "y":0
        }, 
        {
         "color":"#ffff00",
         "draworder":"topdown",
         "id":5,
         "name":"wiring - lights & guns",
         "objects":[],
         "opacity":1,
         "type":"objectgroup",
         "visible":true,
         "x":0,
         "y":0
        }, 
        {
         "color":"#ff0000",
         "draworder":"topdown",
         "id":6,
         "name":"monsters & npcs",
         "objects":[],
         "opacity":1,
         "type":"objectgroup",
         "visible":true,
         "x":0,
         "y":0
        }, 
        {
         "color":"#00ffff",
         "draworder":"topdown",
         "id":7,
         "name":"wiring - locked door",
         "objects":[],
         "opacity":1,
         "type":"objectgroup",
         "visible":true,
         "x":0,
         "y":0
        }, 
        {
         "draworder":"topdown",
         "id":8,
         "name":"outside the map",
         "objects":[],
         "opacity":1,
         "type":"objectgroup",
         "visible":true,
         "x":0,
         "y":0
        }, 
        {
         "draworder":"topdown",
         "id":9,
         "name":"anchors etc",
         "objects":[
                {
                 "gid":201,
                 "height":8,
                 "id":874,
                 "name":"",
                 "rotation":0,
                 "type":"",
                 "visible":true,
                 "width":8,
                 "x":120,
                 "y":296
                }],
         "opacity":1,
         "type":"objectgroup",
         "visible":true,
         "x":0,
         "y":0
        }, 
        {
         "draworder":"topdown",
         "id":10,
         "name":"items",
         "objects":[],
         "opacity":1,
         "type":"objectgroup",
         "visible":true,
         "x":0,
         "y":0
        }],
 "nextlayerid":11,
 "nextobjectid":1083,
 "orientation":"orthogonal",
 "renderorder":"right-down",
 "tiledversion":"1.4.2",
 "tileheight":8,
 "tilesets":[
        {
         "firstgid":1,
         "source":"..\/..\/..\/..\/..\/assets\/packed\/tilesets\/packed\/materials.json"
        }, 
        {
         "firstgid":198,
         "source":"..\/..\/..\/..\/..\/assets\/packed\/tilesets\/packed\/miscellaneous.json"
        }, 
        {
         "firstgid":222,
         "source":"..\/..\/..\/..\/..\/assets\/packed\/tilesets\/packed\/liquids.json"
        }, 
        {
         "firstgid":250,
         "source":"..\/..\/..\/..\/..\/assets\/packed\/tilesets\/packed\/supports.json"
        }, 
        {
         "firstgid":287,
         "source":"..\/..\/..\/..\/..\/assets\/packed\/tilesets\/packed\/objects-by-race\/generic.json"
        }, 
        {
         "firstgid":2271,
         "source":"..\/..\/..\/..\/..\/assets\/packed\/tilesets\/packed\/objects-by-race\/ancient.json"
        }, 
        {
         "firstgid":2434,
         "source":"..\/..\/..\/..\/..\/assets\/packed\/tilesets\/packed\/objects-by-race\/apex.json"
        }, 
        {
         "firstgid":2805,
         "source":"..\/..\/..\/..\/..\/assets\/packed\/tilesets\/packed\/objects-by-race\/avian.json"
        }, 
        {
         "firstgid":3110,
         "source":"..\/..\/..\/..\/..\/assets\/packed\/tilesets\/packed\/objects-by-race\/floran.json"
        }, 
        {
         "firstgid":3305,
         "source":"..\/..\/..\/..\/..\/assets\/packed\/tilesets\/packed\/objects-by-race\/glitch.json"
        }, 
        {
         "firstgid":3531,
         "source":"..\/..\/..\/..\/..\/assets\/packed\/tilesets\/packed\/objects-by-race\/human.json"
        }, 
        {
         "firstgid":3819,
         "source":"..\/..\/..\/..\/..\/assets\/packed\/tilesets\/packed\/objects-by-race\/hylotl.json"
        }, 
        {
         "firstgid":4051,
         "source":"..\/..\/..\/..\/..\/assets\/packed\/tilesets\/packed\/objects-by-race\/novakid.json"
        }, 
        {
         "firstgid":4115,
         "source":"..\/..\/..\/..\/..\/assets\/packed\/tilesets\/packed\/objects-by-category\/crafting.json"
        }, 
        {
         "firstgid":4195,
         "source":"..\/..\/..\/..\/..\/assets\/packed\/tilesets\/packed\/objects-by-category\/decorative.json"
        }, 
        {
         "firstgid":5636,
         "source":"..\/..\/..\/..\/..\/assets\/packed\/tilesets\/packed\/objects-by-category\/door.json"
        }, 
        {
         "firstgid":5768,
         "source":"..\/..\/..\/..\/..\/assets\/packed\/tilesets\/packed\/objects-by-category\/farmable.json"
        }, 
        {
         "firstgid":5843,
         "source":"..\/..\/..\/..\/..\/assets\/packed\/tilesets\/packed\/objects-by-category\/furniture.json"
        }, 
        {
         "firstgid":6197,
         "source":"..\/..\/..\/..\/..\/assets\/packed\/tilesets\/packed\/objects-by-category\/light.json"
        }, 
        {
         "firstgid":6655,
         "source":"..\/..\/..\/..\/..\/assets\/packed\/tilesets\/packed\/objects-by-category\/other.json"
        }, 
        {
         "firstgid":6967,
         "source":"..\/..\/..\/..\/..\/assets\/packed\/tilesets\/packed\/objects-by-category\/pot.json"
        }, 
        {
         "firstgid":7264,
         "source":"..\/..\/..\/..\/..\/assets\/packed\/tilesets\/packed\/objects-by-category\/sapling.json"
        }, 
        {
         "firstgid":7265,
         "source":"..\/..\/..\/..\/..\/assets\/packed\/tilesets\/packed\/objects-by-category\/spawner.json"
        }, 
        {
         "firstgid":7281,
         "source":"..\/..\/..\/..\/..\/assets\/packed\/tilesets\/packed\/objects-by-category\/storage.json"
        }, 
        {
         "firstgid":7515,
         "source":"..\/..\/..\/..\/..\/assets\/packed\/tilesets\/packed\/objects-by-category\/teleporter.json"
        }, 
        {
         "firstgid":7557,
         "source":"..\/..\/..\/..\/..\/assets\/packed\/tilesets\/packed\/objects-by-category\/tools.json"
        }, 
        {
         "firstgid":7562,
         "source":"..\/..\/..\/..\/..\/assets\/packed\/tilesets\/packed\/objects-by-category\/trap.json"
        }, 
        {
         "firstgid":7766,
         "source":"..\/..\/..\/..\/..\/assets\/packed\/tilesets\/packed\/objects-by-category\/wire.json"
        }, 
        {
         "firstgid":7988,
         "source":"..\/..\/..\/..\/..\/assets\/packed\/tilesets\/packed\/objects-by-type\/container.json"
        }, 
        {
         "firstgid":8273,
         "source":"..\/..\/..\/..\/..\/assets\/packed\/tilesets\/packed\/objects-by-type\/farmable.json"
        }, 
        {
         "firstgid":8351,
         "source":"..\/..\/..\/..\/..\/assets\/packed\/tilesets\/packed\/objects-by-type\/loungeable.json"
        }, 
        {
         "firstgid":8632,
         "source":"..\/..\/..\/..\/..\/assets\/packed\/tilesets\/packed\/objects-by-type\/noisy.json"
        }, 
        {
         "firstgid":8673,
         "source":"..\/..\/..\/..\/..\/assets\/packed\/tilesets\/packed\/objects-by-type\/teleporter.json"
        }, 
        {
         "firstgid":8700,
         "source":"..\/..\/..\/..\/..\/assets\/packed\/tilesets\/packed\/objects-by-category\/railpoint.json"
        }, 
        {
         "firstgid":8705,
         "source":"..\/..\/..\/..\/..\/assets\/packed\/tilesets\/packed\/objects-by-colonytag\/station.json"
        }, 
        {
         "firstgid":8735,
         "source":"..\/..\/..\/..\/..\/assets\/packed\/tilesets\/packed\/objects-by-colonytag\/outpost.json"
        }, 
        {
         "firstgid":8839,
         "source":"..\/..\/..\/..\/..\/assets\/packed\/tilesets\/packed\/objects-by-colonytag\/peacekeeper.json"
        }],
 "tilewidth":8,
 "type":"map",
 "version":1.4,
 "width":168
}