{ "backgroundcolor":"#000000",
 "height":16,
 "layers":[
        {
         "data":[2, 2, 2, 2, 2, 2, 2, 2, 2, 2, 2, 2, 2, 2, 2, 2, 2, 2, 2, 2, 2, 2, 2, 2, 2, 2, 2, 2, 2, 2, 2, 2, 2, 2, 2, 2, 2, 2, 2, 2, 2, 2, 2, 2, 2, 2, 2, 2, 2, 2, 2, 2, 2, 2, 2, 2, 2, 2, 2, 2, 2, 2, 112, 112, 112, 112, 112, 112, 112, 112, 112, 112, 112, 112, 112, 112, 112, 112, 112, 112, 112, 112, 112, 112, 112, 112, 112, 112, 2, 2, 2, 2, 112, 112, 100, 188, 100, 112, 112, 112, 112, 112, 112, 112, 112, 112, 112, 112, 112, 112, 112, 112, 112, 100, 188, 100, 112, 112, 2, 2, 2, 2, 112, 112, 100, 188, 100, 112, 112, 112, 112, 112, 112, 112, 112, 112, 112, 112, 112, 112, 112, 112, 112, 100, 188, 100, 112, 112, 2, 2, 2, 2, 112, 112, 100, 188, 100, 112, 112, 112, 112, 112, 112, 112, 112, 112, 112, 112, 112, 112, 112, 112, 112, 100, 188, 100, 112, 112, 2, 2, 2, 2, 112, 112, 100, 188, 100, 112, 112, 112, 112, 112, 112, 112, 112, 112, 112, 112, 112, 112, 112, 112, 112, 100, 188, 100, 112, 112, 2, 2, 2, 2, 112, 112, 100, 188, 100, 112, 112, 112, 112, 112, 112, 112, 112, 112, 112, 112, 112, 112, 112, 112, 112, 100, 188, 100, 112, 112, 2, 2, 2, 2, 112, 112, 100, 188, 100, 112, 112, 112, 112, 112, 112, 112, 112, 112, 112, 112, 112, 112, 112, 112, 112, 100, 188, 100, 112, 112, 2, 2, 2, 2, 112, 112, 100, 188, 100, 112, 112, 112, 112, 112, 112, 112, 112, 112, 112, 112, 112, 112, 112, 112, 112, 100, 188, 100, 112, 112, 2, 2, 2, 2, 112, 112, 100, 188, 100, 112, 112, 112, 112, 112, 112, 112, 112, 112, 112, 112, 112, 112, 112, 112, 112, 100, 188, 100, 112, 112, 2, 2, 2, 2, 112, 112, 100, 188, 100, 112, 112, 112, 112, 112, 112, 112, 112, 112, 112, 112, 112, 112, 112, 112, 112, 100, 188, 100, 112, 112, 2, 2, 2, 2, 112, 112, 100, 188, 100, 112, 112, 112, 112, 112, 112, 112, 112, 112, 112, 112, 112, 112, 112, 112, 112, 100, 188, 100, 112, 112, 2, 2, 2, 2, 112, 112, 112, 112, 112, 112, 112, 112, 112, 112, 112, 112, 112, 112, 112, 112, 112, 112, 112, 112, 112, 112, 112, 112, 112, 112, 2, 2, 2, 2, 2, 2, 2, 2, 2, 2, 2, 2, 2, 2, 2, 2, 2, 2, 2, 2, 2, 2, 2, 2, 2, 2, 2, 2, 2, 2, 2, 2, 2, 2, 2, 2, 2, 2, 2, 2, 2, 2, 2, 2, 2, 2, 2, 2, 2, 2, 2, 2, 2, 2, 2, 2, 2, 2, 2, 2, 2, 2],
         "height":16,
         "name":"back",
         "opacity":0.5,
         "type":"tilelayer",
         "visible":true,
         "width":30,
         "x":0,
         "y":0
        }, 
        {
         "data":[0, 0, 0, 0, 0, 0, 0, 0, 0, 0, 0, 0, 0, 0, 0, 0, 0, 0, 0, 0, 0, 0, 0, 0, 0, 0, 0, 0, 0, 0, 0, 0, 0, 0, 0, 0, 0, 0, 0, 0, 0, 0, 0, 0, 0, 0, 0, 0, 0, 0, 0, 0, 0, 0, 0, 0, 0, 0, 0, 0, 0, 0, 44, 44, 44, 44, 44, 44, 44, 44, 44, 44, 44, 44, 44, 44, 44, 44, 44, 44, 44, 44, 44, 44, 44, 44, 44, 44, 0, 0, 0, 0, 0, 0, 0, 0, 0, 0, 0, 0, 0, 0, 0, 0, 0, 0, 0, 0, 0, 0, 0, 0, 0, 0, 0, 0, 0, 0, 0, 0, 0, 0, 0, 0, 0, 0, 0, 0, 0, 0, 0, 0, 0, 0, 0, 0, 0, 0, 0, 0, 0, 0, 0, 0, 0, 0, 0, 0, 0, 0, 0, 0, 0, 0, 0, 0, 0, 0, 0, 0, 0, 0, 0, 0, 0, 0, 0, 0, 0, 0, 0, 0, 0, 0, 0, 0, 0, 0, 0, 0, 0, 0, 0, 0, 0, 0, 0, 0, 0, 0, 0, 0, 0, 0, 0, 0, 0, 0, 0, 0, 0, 0, 0, 0, 0, 0, 0, 0, 0, 0, 0, 0, 0, 0, 0, 0, 0, 0, 0, 0, 0, 0, 0, 0, 0, 0, 0, 0, 0, 0, 0, 0, 0, 0, 0, 0, 0, 0, 0, 0, 0, 0, 0, 0, 0, 0, 0, 0, 0, 0, 0, 0, 0, 0, 0, 0, 0, 0, 0, 0, 0, 0, 0, 0, 0, 0, 0, 0, 0, 0, 0, 0, 0, 0, 0, 0, 0, 0, 0, 0, 0, 0, 0, 0, 0, 0, 0, 0, 0, 0, 0, 0, 0, 0, 0, 0, 0, 0, 0, 0, 0, 0, 0, 0, 0, 0, 0, 0, 0, 0, 0, 0, 0, 0, 0, 0, 0, 0, 0, 0, 0, 0, 0, 0, 0, 0, 0, 0, 0, 0, 0, 0, 0, 0, 0, 0, 0, 0, 0, 0, 0, 0, 0, 0, 0, 0, 0, 0, 0, 0, 0, 0, 0, 0, 0, 0, 0, 0, 0, 0, 0, 0, 0, 0, 0, 0, 0, 0, 0, 0, 0, 0, 0, 0, 0, 0, 0, 0, 0, 0, 0, 0, 0, 0, 0, 0, 0, 0, 0, 0, 0, 0, 44, 44, 44, 44, 44, 44, 44, 44, 44, 44, 44, 44, 44, 44, 44, 44, 44, 44, 44, 44, 44, 44, 44, 44, 44, 44, 0, 0, 0, 0, 0, 0, 0, 0, 0, 0, 0, 0, 0, 0, 0, 0, 0, 0, 0, 0, 0, 0, 0, 0, 0, 0, 0, 0, 0, 0, 0, 0, 0, 0, 0, 0, 0, 0, 0, 0, 0, 0, 0, 0, 0, 0, 0, 0, 0, 0, 0, 0, 0, 0, 0, 0, 0, 0, 0, 0, 0, 0],
         "height":16,
         "name":"front",
         "opacity":1,
         "type":"tilelayer",
         "visible":true,
         "width":30,
         "x":0,
         "y":0
        }, 
        {
         "draworder":"topdown",
         "height":200,
         "name":"objects",
         "objects":[
                {
                 "gid":3967,
                 "height":40,
                 "id":3,
                 "name":"",
                 "properties":
                    {

                    },
                 "rotation":0,
                 "type":"",
                 "visible":true,
                 "width":25,
                 "x":96,
                 "y":104
                }, 
                {
                 "gid":3967,
                 "height":40,
                 "id":4,
                 "name":"",
                 "properties":
                    {

                    },
                 "rotation":0,
                 "type":"",
                 "visible":true,
                 "width":25,
                 "x":128,
                 "y":104
                }, 
                {
                 "gid":1579,
                 "height":24,
                 "id":5,
                 "name":"",
                 "properties":
                    {

                    },
                 "rotation":0,
                 "type":"",
                 "visible":true,
                 "width":16,
                 "x":40,
                 "y":104
                }, 
                {
                 "gid":1579,
                 "height":24,
                 "id":6,
                 "name":"",
                 "properties":
                    {

                    },
                 "rotation":0,
                 "type":"",
                 "visible":true,
                 "width":16,
                 "x":56,
                 "y":104
                }, 
                {
                 "gid":1579,
                 "height":24,
                 "id":7,
                 "name":"",
                 "properties":
                    {

                    },
                 "rotation":0,
                 "type":"",
                 "visible":true,
                 "width":16,
                 "x":48,
                 "y":80
                }, 
                {
                 "gid":1579,
                 "height":24,
                 "id":8,
                 "name":"",
                 "properties":
                    {

                    },
                 "rotation":0,
                 "type":"",
                 "visible":true,
                 "width":16,
                 "x":72,
                 "y":104
                }, 
                {
                 "gid":1104,
                 "height":24,
                 "id":9,
                 "name":"",
                 "properties":
                    {

                    },
                 "rotation":0,
                 "type":"",
                 "visible":true,
                 "width":16,
                 "x":176,
                 "y":80
                }, 
                {
                 "gid":1104,
                 "height":24,
                 "id":10,
                 "name":"",
                 "properties":
                    {

                    },
                 "rotation":0,
                 "type":"",
                 "visible":true,
                 "width":16,
                 "x":184,
                 "y":104
                }, 
                {
                 "gid":1104,
                 "height":24,
                 "id":11,
                 "name":"",
                 "properties":
                    {

                    },
                 "rotation":0,
                 "type":"",
                 "visible":true,
                 "width":16,
                 "x":168,
                 "y":104
                }, 
                {
                 "gid":2649,
                 "height":24,
                 "id":12,
                 "name":"",
                 "properties":
                    {

                    },
                 "rotation":0,
                 "type":"",
                 "visible":true,
                 "width":40,
                 "x":104,
                 "y":48
                }, 
                {
                 "gid":932,
                 "height":16,
                 "id":13,
                 "name":"",
                 "properties":
                    {

                    },
                 "rotation":0,
                 "type":"",
                 "visible":true,
                 "width":16,
                 "x":160,
                 "y":48
                }, 
                {
                 "gid":2725,
                 "height":16,
                 "id":14,
                 "name":"",
                 "properties":
                    {

                    },
                 "rotation":0,
                 "type":"",
                 "visible":true,
                 "width":24,
                 "x":64,
                 "y":40
                }],
         "opacity":1,
         "type":"objectgroup",
         "visible":true,
         "width":200,
         "x":0,
         "y":0
        }, 
        {
         "draworder":"topdown",
         "height":200,
         "name":"npcs and monsters",
         "objects":[],
         "opacity":1,
         "type":"objectgroup",
         "visible":true,
         "width":200,
         "x":0,
         "y":0
        }, 
        {
         "draworder":"topdown",
         "height":200,
         "name":"mods and stagehands",
         "objects":[
                {
                 "gid":15,
                 "height":8,
                 "id":1,
                 "name":"",
                 "properties":
                    {

                    },
                 "rotation":0,
                 "type":"",
                 "visible":true,
                 "width":8,
                 "x":8,
                 "y":104
                }, 
                {
                 "gid":15,
                 "height":8,
                 "id":2,
                 "name":"",
                 "properties":
                    {

                    },
                 "rotation":0,
                 "type":"",
                 "visible":true,
                 "width":8,
                 "x":224,
                 "y":104
                }],
         "opacity":1,
         "type":"objectgroup",
         "visible":true,
         "width":200,
         "x":0,
         "y":0
        }, 
        {
         "draworder":"topdown",
         "height":200,
         "name":"wires",
         "objects":[],
         "opacity":1,
         "type":"objectgroup",
         "visible":true,
         "width":200,
         "x":0,
         "y":0
        }],
 "nextobjectid":15,
 "orientation":"orthogonal",
 "properties":
    {

    },
 "renderorder":"right-down",
 "tileheight":8,
 "tilesets":[
        {
         "firstgid":1,
         "source":"..\/..\/..\/..\/..\/assets\/packed\/tilesets\/packed\/miscellaneous.json"
        }, 
        {
         "firstgid":21,
         "source":"..\/..\/..\/..\/..\/assets\/packed\/tilesets\/packed\/materials.json"
        }, 
        {
         "firstgid":211,
         "source":"..\/..\/..\/..\/..\/assets\/packed\/tilesets\/packed\/supports.json"
        }, 
        {
         "firstgid":247,
         "source":"..\/..\/..\/..\/..\/assets\/packed\/tilesets\/packed\/liquids.json"
        }, 
        {
         "firstgid":275,
         "source":"..\/..\/..\/..\/..\/assets\/packed\/tilesets\/packed\/objects-by-category\/breakable.json"
        }, 
        {
         "firstgid":579,
         "source":"..\/..\/..\/..\/..\/assets\/packed\/tilesets\/packed\/objects-by-category\/bug.json"
        }, 
        {
         "firstgid":622,
         "source":"..\/..\/..\/..\/..\/assets\/packed\/tilesets\/packed\/objects-by-category\/crafting.json"
        }, 
        {
         "firstgid":701,
         "source":"..\/..\/..\/..\/..\/assets\/packed\/tilesets\/packed\/objects-by-category\/decorative.json"
        }, 
        {
         "firstgid":2061,
         "source":"..\/..\/..\/..\/..\/assets\/packed\/tilesets\/packed\/objects-by-category\/door.json"
        }, 
        {
         "firstgid":2178,
         "source":"..\/..\/..\/..\/..\/assets\/packed\/tilesets\/packed\/objects-by-category\/furniture.json"
        }, 
        {
         "firstgid":2511,
         "source":"..\/..\/..\/..\/..\/assets\/packed\/tilesets\/packed\/objects-by-category\/light.json"
        }, 
        {
         "firstgid":2932,
         "source":"..\/..\/..\/..\/..\/assets\/packed\/tilesets\/packed\/objects-by-category\/other.json"
        }, 
        {
         "firstgid":3230,
         "source":"..\/..\/..\/..\/..\/assets\/packed\/tilesets\/packed\/objects-by-category\/rail.json"
        }, 
        {
         "firstgid":3234,
         "source":"..\/..\/..\/..\/..\/assets\/packed\/tilesets\/packed\/objects-by-category\/refinery.json"
        }, 
        {
         "firstgid":3235,
         "source":"..\/..\/..\/..\/..\/assets\/packed\/tilesets\/packed\/objects-by-category\/seed.json"
        }, 
        {
         "firstgid":3311,
         "source":"..\/..\/..\/..\/..\/assets\/packed\/tilesets\/packed\/objects-by-category\/spawner.json"
        }, 
        {
         "firstgid":3327,
         "source":"..\/..\/..\/..\/..\/assets\/packed\/tilesets\/packed\/objects-by-category\/storage.json"
        }, 
        {
         "firstgid":3548,
         "source":"..\/..\/..\/..\/..\/assets\/packed\/tilesets\/packed\/objects-by-category\/techmanagement.json"
        }, 
        {
         "firstgid":3549,
         "source":"..\/..\/..\/..\/..\/assets\/packed\/tilesets\/packed\/objects-by-category\/trap.json"
        }, 
        {
         "firstgid":3753,
         "source":"..\/..\/..\/..\/..\/assets\/packed\/tilesets\/packed\/objects-by-category\/wire.json"
        }, 
        {
         "firstgid":3957,
         "source":"..\/..\/..\/tilesets\/extradungeons-custom\/modstuff.json"
        }],
 "tilewidth":8,
 "version":1,
 "width":30
}