{ "backgroundcolor":"#000000",
 "height":60,
 "layers":[
        {
         "compression":"zlib",
         "data":"eJzt2UEOgyAQBVDuwIV7A2\/iyl3PUM\/UJg0NNagzzgAj83\/y4waFZww2dQnhsaAoiqIoiqIoqtpgPB6Me\/Hi3MaTNcWTNQXeca0p8I4dT9YUqXeK5aPVaHi3tRypd91YV3hNBV5e4FVcXIVIvLkx1foeDS898MJrLRpeym\/Ko7HSWvTWMnPT+nnuac29V8x380r\/36jhLV1rVO9aaE0v16zpLVnPzFKrRy\/HfBev1jekO3g1vxNe2UtavY+4ToqduxZNa2keDWPq83O9o77i9zjH\/07hpETXHI\/nz1vbmnv3uuf93ZMTL9UqNXPnsVJP3hbPc++mdWruWZbt2k7L5ppWa+5W1t7m1k6JmXpeaVxPJ9dPHd97\/RJz73Wg\/voGJrJ\/gw==",
         "encoding":"base64",
         "height":60,
         "name":"back",
         "opacity":0.5,
         "type":"tilelayer",
         "visible":true,
         "width":60,
         "x":0,
         "y":0
        }, 
        {
         "compression":"zlib",
         "data":"eJzt1gEKgzAMQNHewYPvJruAlxsFC4G5Lm1iTPE\/CNtEXb9uYCkAAAAAAAAAAAAAgFmvrb+tva+vbX7t8++8GciG3uez0Z4jk16PdTJ6Wm\/1pNbGutaVWit6Y4+PRm\/s8dHojT0+Gr3f23vPFCv1Wp+PIp+v9mPeW380+8jR0pyrrdGrVc5Ik7Vb2ynHs3VmvK6L9vvu7LWufXSsolot16UUn1bP9tHfd+Q9varZu\/PqVsmj8e7\/6iiv33f2Tml2rTP7ZTR6TzLdu1krrx1r+wDYr3v6",
         "encoding":"base64",
         "height":60,
         "name":"front",
         "opacity":1,
         "type":"tilelayer",
         "visible":true,
         "width":60,
         "x":0,
         "y":0
        }, 
        {
         "color":"#5555ff",
         "draworder":"topdown",
         "height":0,
         "name":"mods",
         "objects":[],
         "opacity":1,
         "type":"objectgroup",
         "visible":true,
         "width":0,
         "x":0,
         "y":0
        }, 
        {
         "color":"#ff0000",
         "draworder":"topdown",
         "height":0,
         "name":"objects",
         "objects":[
                {
                 "gid":4111,
                 "height":16,
                 "id":718,
                 "name":"",
                 "properties":
                    {

                    },
                 "rotation":0,
                 "type":"",
                 "visible":true,
                 "width":16,
                 "x":288,
                 "y":384
                }, 
                {
                 "gid":4112,
                 "height":16,
                 "id":719,
                 "name":"",
                 "properties":
                    {

                    },
                 "rotation":0,
                 "type":"",
                 "visible":true,
                 "width":16,
                 "x":304,
                 "y":384
                }, 
                {
                 "gid":4096,
                 "height":16,
                 "id":720,
                 "name":"",
                 "properties":
                    {

                    },
                 "rotation":0,
                 "type":"",
                 "visible":true,
                 "width":16,
                 "x":264,
                 "y":384
                }, 
                {
                 "gid":2147487489,
                 "height":16,
                 "id":735,
                 "name":"",
                 "properties":
                    {
                     "parameters":"{\"treasurePools\":[\"ffbasicTreasure\"]}"
                    },
                 "rotation":0,
                 "type":"",
                 "visible":true,
                 "width":16,
                 "x":184,
                 "y":368
                }],
         "opacity":1,
         "type":"objectgroup",
         "visible":true,
         "width":0,
         "x":0,
         "y":0
        }, 
        {
         "color":"#ffff00",
         "draworder":"topdown",
         "height":0,
         "name":"wiring - lights & guns",
         "objects":[],
         "opacity":1,
         "type":"objectgroup",
         "visible":true,
         "width":0,
         "x":0,
         "y":0
        }, 
        {
         "color":"#ff0000",
         "draworder":"topdown",
         "height":0,
         "name":"monsters & npcs",
         "objects":[
                {
                 "height":8,
                 "id":729,
                 "name":"",
                 "properties":
                    {
                     "npc":"floran,human,avian,apex",
                     "typeName":"fucannibal"
                    },
                 "rotation":0,
                 "type":"",
                 "visible":true,
                 "width":8,
                 "x":160,
                 "y":328
                }, 
                {
                 "height":8,
                 "id":731,
                 "name":"",
                 "properties":
                    {
                     "npc":"floran,human,avian,apex",
                     "typeName":"fucannibal"
                    },
                 "rotation":0,
                 "type":"",
                 "visible":true,
                 "width":8,
                 "x":96,
                 "y":320
                }, 
                {
                 "height":8,
                 "id":732,
                 "name":"",
                 "properties":
                    {
                     "npc":"floran,human,avian,apex",
                     "typeName":"fucannibal"
                    },
                 "rotation":0,
                 "type":"",
                 "visible":true,
                 "width":8,
                 "x":224,
                 "y":200
                }],
         "opacity":1,
         "type":"objectgroup",
         "visible":true,
         "width":0,
         "x":0,
         "y":0
        }, 
        {
         "color":"#00ffff",
         "draworder":"topdown",
         "height":0,
         "name":"wiring - locked door",
         "objects":[],
         "opacity":1,
         "type":"objectgroup",
         "visible":true,
         "width":0,
         "x":0,
         "y":0
        }, 
        {
         "draworder":"topdown",
         "height":0,
         "name":"outside the map",
         "objects":[],
         "opacity":1,
         "type":"objectgroup",
         "visible":true,
         "width":0,
         "x":0,
         "y":0
        }, 
        {
         "draworder":"topdown",
         "height":0,
         "name":"anchors etc",
         "objects":[
                {
                 "gid":183,
                 "height":8,
                 "id":708,
                 "name":"",
                 "properties":
                    {

                    },
                 "rotation":0,
                 "type":"",
                 "visible":true,
                 "width":8,
                 "x":392,
                 "y":104
                }, 
                {
                 "gid":183,
                 "height":8,
                 "id":709,
                 "name":"",
                 "properties":
                    {

                    },
                 "rotation":0,
                 "type":"",
                 "visible":true,
                 "width":8,
                 "x":240,
                 "y":104
                }, 
                {
                 "gid":183,
                 "height":8,
                 "id":710,
                 "name":"",
                 "properties":
                    {

                    },
                 "rotation":0,
                 "type":"",
                 "visible":true,
                 "width":8,
                 "x":80,
                 "y":104
                }, 
                {
                 "gid":183,
                 "height":8,
                 "id":711,
                 "name":"",
                 "properties":
                    {

                    },
                 "rotation":0,
                 "type":"",
                 "visible":true,
                 "width":8,
                 "x":80,
                 "y":368
                }, 
                {
                 "gid":183,
                 "height":8,
                 "id":712,
                 "name":"",
                 "properties":
                    {

                    },
                 "rotation":0,
                 "type":"",
                 "visible":true,
                 "width":8,
                 "x":392,
                 "y":368
                }, 
                {
                 "gid":184,
                 "height":8,
                 "id":713,
                 "name":"",
                 "properties":
                    {

                    },
                 "rotation":0,
                 "type":"",
                 "visible":true,
                 "width":8,
                 "x":400,
                 "y":400
                }, 
                {
                 "gid":184,
                 "height":8,
                 "id":714,
                 "name":"",
                 "properties":
                    {

                    },
                 "rotation":0,
                 "type":"",
                 "visible":true,
                 "width":8,
                 "x":72,
                 "y":400
                }, 
                {
                 "gid":183,
                 "height":8,
                 "id":715,
                 "name":"",
                 "properties":
                    {

                    },
                 "rotation":0,
                 "type":"",
                 "visible":true,
                 "width":8,
                 "x":464,
                 "y":240
                }, 
                {
                 "gid":183,
                 "height":8,
                 "id":716,
                 "name":"",
                 "properties":
                    {

                    },
                 "rotation":0,
                 "type":"",
                 "visible":true,
                 "width":8,
                 "x":8,
                 "y":240
                }, 
                {
                 "gid":195,
                 "height":8,
                 "id":722,
                 "name":"",
                 "properties":
                    {

                    },
                 "rotation":0,
                 "type":"",
                 "visible":true,
                 "width":8,
                 "x":392,
                 "y":104
                }, 
                {
                 "gid":195,
                 "height":8,
                 "id":723,
                 "name":"",
                 "properties":
                    {

                    },
                 "rotation":0,
                 "type":"",
                 "visible":true,
                 "width":8,
                 "x":240,
                 "y":104
                }, 
                {
                 "gid":195,
                 "height":8,
                 "id":724,
                 "name":"",
                 "properties":
                    {

                    },
                 "rotation":0,
                 "type":"",
                 "visible":true,
                 "width":8,
                 "x":80,
                 "y":104
                }, 
                {
                 "gid":195,
                 "height":8,
                 "id":725,
                 "name":"",
                 "properties":
                    {

                    },
                 "rotation":0,
                 "type":"",
                 "visible":true,
                 "width":8,
                 "x":8,
                 "y":240
                }, 
                {
                 "gid":195,
                 "height":8,
                 "id":726,
                 "name":"",
                 "properties":
                    {

                    },
                 "rotation":0,
                 "type":"",
                 "visible":true,
                 "width":8,
                 "x":464,
                 "y":240
                }, 
                {
                 "gid":195,
                 "height":8,
                 "id":727,
                 "name":"",
                 "properties":
                    {

                    },
                 "rotation":0,
                 "type":"",
                 "visible":true,
                 "width":8,
                 "x":392,
                 "y":368
                }, 
                {
                 "gid":195,
                 "height":8,
                 "id":728,
                 "name":"",
                 "properties":
                    {

                    },
                 "rotation":0,
                 "type":"",
                 "visible":true,
                 "width":8,
                 "x":80,
                 "y":368
                }],
         "opacity":1,
         "type":"objectgroup",
         "visible":true,
         "width":0,
         "x":0,
         "y":0
        }, 
        {
         "draworder":"topdown",
         "height":0,
         "name":"items",
         "objects":[],
         "opacity":1,
         "type":"objectgroup",
         "visible":true,
         "width":0,
         "x":0,
         "y":0
        }],
 "nextobjectid":736,
 "orientation":"orthogonal",
 "properties":
    {

    },
 "renderorder":"right-down",
 "tileheight":8,
 "tilesets":[
        {
         "firstgid":1,
         "source":"..\/..\/..\/..\/..\/..\/assets\/packed\/tilesets\/packed\/materials.json"
        }, 
        {
         "firstgid":179,
         "source":"..\/..\/..\/..\/..\/..\/assets\/packed\/tilesets\/packed\/miscellaneous.json"
        }, 
        {
         "firstgid":197,
         "source":"..\/..\/..\/..\/..\/..\/assets\/packed\/tilesets\/packed\/liquids.json"
        }, 
        {
         "firstgid":223,
         "source":"..\/..\/..\/..\/..\/..\/assets\/packed\/tilesets\/packed\/supports.json"
        }, 
        {
         "firstgid":257,
         "source":"..\/..\/..\/..\/..\/..\/assets\/packed\/tilesets\/packed\/objects-by-race\/generic.json"
        }, 
        {
         "firstgid":1556,
         "source":"..\/..\/..\/..\/..\/..\/assets\/packed\/tilesets\/packed\/objects-by-category\/decorative.json"
        }, 
        {
         "firstgid":2554,
         "source":"..\/..\/..\/..\/..\/..\/assets\/packed\/tilesets\/packed\/objects-by-category\/door.json"
        }, 
        {
         "firstgid":2647,
         "source":"..\/..\/..\/..\/..\/..\/assets\/packed\/tilesets\/packed\/objects-by-category\/farmable.json"
        }, 
        {
         "firstgid":2719,
         "source":"..\/..\/..\/..\/..\/..\/assets\/packed\/tilesets\/packed\/objects-by-category\/furniture.json"
        }, 
        {
         "firstgid":3000,
         "source":"..\/..\/..\/..\/..\/..\/assets\/packed\/tilesets\/packed\/objects-by-category\/light.json"
        }, 
        {
         "firstgid":3371,
         "source":"..\/..\/..\/..\/..\/..\/assets\/packed\/tilesets\/packed\/objects-by-category\/other.json"
        }, 
        {
         "firstgid":3565,
         "source":"..\/..\/..\/..\/..\/..\/assets\/packed\/tilesets\/packed\/objects-by-category\/pot.json"
        }, 
        {
         "firstgid":3825,
         "source":"..\/..\/..\/..\/..\/..\/assets\/packed\/tilesets\/packed\/objects-by-category\/sapling.json"
        }, 
        {
         "firstgid":3826,
         "source":"..\/..\/..\/..\/..\/..\/assets\/packed\/tilesets\/packed\/objects-by-category\/spawner.json"
        }, 
        {
         "firstgid":3841,
         "source":"..\/..\/..\/..\/..\/..\/assets\/packed\/tilesets\/packed\/objects-by-category\/storage.json"
        }, 
        {
         "firstgid":4036,
         "source":"..\/..\/..\/..\/..\/..\/assets\/packed\/tilesets\/packed\/objects-by-category\/teleporter.json"
        }, 
        {
         "firstgid":4060,
         "source":"..\/..\/..\/..\/..\/..\/assets\/packed\/tilesets\/packed\/objects-by-category\/tools.json"
        }, 
        {
         "firstgid":4065,
         "source":"..\/..\/..\/..\/..\/..\/assets\/packed\/tilesets\/packed\/objects-by-category\/trap.json"
        }, 
        {
         "firstgid":4240,
         "source":"..\/..\/..\/..\/..\/..\/assets\/packed\/tilesets\/packed\/objects-by-category\/wire.json"
        }, 
        {
         "firstgid":4386,
         "source":"..\/..\/..\/..\/..\/..\/assets\/packed\/tilesets\/packed\/objects-by-type\/container.json"
        }, 
        {
         "firstgid":4624,
         "source":"..\/..\/..\/..\/..\/..\/assets\/packed\/tilesets\/packed\/objects-by-type\/farmable.json"
        }, 
        {
         "firstgid":4697,
         "source":"..\/..\/..\/..\/..\/..\/assets\/packed\/tilesets\/packed\/objects-by-type\/loungeable.json"
        }, 
        {
         "firstgid":4908,
         "source":"..\/..\/..\/..\/..\/..\/assets\/packed\/tilesets\/packed\/objects-by-type\/noisy.json"
        }, 
        {
         "firstgid":4949,
         "source":"..\/..\/..\/..\/..\/..\/assets\/packed\/tilesets\/packed\/objects-by-type\/teleporter.json"
        }, 
        {
         "firstgid":4972,
         "source":"..\/..\/..\/..\/..\/..\/assets\/packed\/tilesets\/packed\/huge-objects.json"
        }, 
        {
         "firstgid":4984,
         "source":"..\/..\/..\/..\/tilesets\/frackinuniverse-custom\/fumaterials2.json"
        }, 
        {
         "firstgid":5071,
         "source":"..\/..\/..\/..\/tilesets\/frackinuniverse-custom\/fuplatforms.json"
        }],
 "tilewidth":8,
 "version":1,
 "width":60
}